Metadata-Version: 1.1
Name: query-builder
Version: 0.0.5
Summary: the query builder ui component
Home-page: UNKNOWN
Author: kalimuthu periyasamy <1995kalimuthu@gmail.com>
Author-email: UNKNOWN
License: MIT
Platform: UNKNOWN
Classifier: Framework :: Dash
